lazyfeed/__init__.py
lazyfeed/app.py
lazyfeed/config_template.toml
lazyfeed/db.py
lazyfeed/decorators.py
lazyfeed/feeds.py
lazyfeed/global.tcss
lazyfeed/http_client.py
lazyfeed/main.py
lazyfeed/messages.py
lazyfeed/models.py
lazyfeed/settings.py
lazyfeed/utils.py
lazyfeed/widgets/__init__.py
lazyfeed/widgets/custom_header.py
lazyfeed/widgets/helpable.py
lazyfeed/widgets/item_screen.py
lazyfeed/widgets/item_table.py
lazyfeed/widgets/rss_feed_tree.py
lazyfeed/widgets/validators.py
lazyfeed/widgets/modals/__init__.py
lazyfeed/widgets/modals/add_feed_modal.py
lazyfeed/widgets/modals/confirm_action_modal.py
lazyfeed/widgets/modals/edit_feed_modal.py
lazyfeed/widgets/modals/help_modal.py
lazyfeed-0.5.9.dist-info/METADATA
lazyfeed-0.5.9.dist-info/WHEEL
lazyfeed-0.5.9.dist-info/entry_points.txt
lazyfeed-0.5.9.dist-info/licenses/LICENSE
lazyfeed-0.5.9.dist-info/RECORD
