Metadata-Version: 2.4
Name: lazyfeed
Version: 0.5.9
Summary: lazyfeed is a fast and simple terminal base RSS/Atom reader built using textual.
Project-URL: homepage, https://dnlzrgz.com/projects/lazyfeed/
Project-URL: source, https://github.com/dnlzrgz/lazyfeed
Project-URL: issues, https://github.com/dnlzrgz/lazyfeed/issues
Project-URL: releases, https://github.com/dnlzrgz/lazyfeed/releases
Author-email: dnlzrgz <contact@dnlzrgz.com>
License-Expression: MIT
License-File: LICENSE
Requires-Python: >=3.12
Requires-Dist: aiohttp[speedups]>=3.10.5
Requires-Dist: click>=8.1.8
Requires-Dist: feedparser>=6.0.11
Requires-Dist: markdownify>=0.14.1
Requires-Dist: pydantic-settings>=2.5.2
Requires-Dist: rich>=13.8.1
Requires-Dist: selectolax>=0.3.27
Requires-Dist: sqlalchemy>=2.0.34
Requires-Dist: textual>=0.79.1
